structclasses/__init__.py
structclasses/base.py
structclasses/decorator.py
structclasses/field/__init__.py
structclasses/field/array.py
structclasses/field/data.py
structclasses/field/enum.py
structclasses/field/meta.py
structclasses/field/primitive.py
structclasses/field/record.py
structclasses/field/union.py
structclasses-0.30.dist-info/licenses/LICENSE
structclasses-0.30.dist-info/WHEEL
structclasses-0.30.dist-info/METADATA
structclasses-0.30.dist-info/RECORD
