Metadata-Version: 2.4
Name: structclasses
Version: 0.30
Summary: Boost your `dataclass` objects with suport for binary serialization.
Author-email: Andreas Stenius <andreas.stenius@gmail.com>
Requires-Python: >=3.10,<3.14
Classifier: Development Status :: 3 - Alpha
Classifier: Intended Audience :: Developers
Classifier: License :: OSI Approved :: MIT License
Classifier: Operating System :: OS Independent
Classifier: Programming Language :: Python :: 3.10
Classifier: Programming Language :: Python :: 3.11
Classifier: Programming Language :: Python :: 3.12
Classifier: Programming Language :: Python :: 3.13
Classifier: Topic :: Software Development :: Libraries :: Python Modules
License-File: LICENSE
Requires-Dist: typing_extensions
Project-URL: Repository, https://github.com/kaos/structclasses
